tokreate/__init__.py
tokreate/logging.py
tokreate/py.typed
tokreate/tokreate.py
tokreate/utils.py
tokreate/providers/__init__.py
tokreate/providers/__main__.py
tokreate/providers/anthropic.py
tokreate/providers/base.py
tokreate/providers/openai_v0.py
tokreate/providers/openai_v1.py
tokreate/providers/toghether.py
tokreate/providers/tulu.py
tokreate-0.3.0.dist-info/METADATA
tokreate-0.3.0.dist-info/WHEEL
tokreate-0.3.0.dist-info/top_level.txt
tokreate-0.3.0.dist-info/RECORD
