Metadata-Version: 2.1
Name: tokreate
Version: 0.3.0
Summary: Unified APIs for making calls to different LLMs.
Author-email: Luca Soldaini <luca@soldaini.net>
License: Apache-2.0
Project-URL: Homepage, https://tokreate.soldaini.net
Project-URL: Source, https://github.com/soldni/tokreate
Project-URL: Tracker, https://github.com/soldni/tokreate/issues
Classifier: Development Status :: 3 - Alpha
Classifier: Typing :: Typed
Requires-Python: >=3.9
Requires-Dist: openai
Requires-Dist: anthropic
Requires-Dist: together
Requires-Dist: jinja2
Requires-Dist: boto3
Requires-Dist: watchtower
Requires-Dist: logging-json ==0.4.0
Requires-Dist: necessary
Provides-Extra: dev
Requires-Dist: black >=22.6.0 ; extra == 'dev'
Requires-Dist: isort >=5.10.1 ; extra == 'dev'
Requires-Dist: mypy >=0.971 ; extra == 'dev'
Requires-Dist: pytest >=5.2 ; extra == 'dev'
Requires-Dist: ipython >=8.4.0 ; extra == 'dev'
Requires-Dist: autopep8 >=1.7.0 ; extra == 'dev'
Requires-Dist: flake8 >=5.0 ; extra == 'dev'
Requires-Dist: ipdb >=0.13.0 ; extra == 'dev'
Requires-Dist: flake8-pyi >=22.8.1 ; extra == 'dev'
Requires-Dist: Flake8-pyproject >=1.1.0 ; extra == 'dev'
